{
    "estacionamento": [
        {
            "id": "1",
            "vaga": "Vaga 1",
            "carro": "",
            "status": "0"
        },
        {
            "id": "2",
            "vaga": "Vaga 2",
            "carro": "",
            "status": "0"
        },
        {
            "id": "3",
            "vaga": "Vaga 3",
            "carro": "",
            "status": "0"
        },
        {
            "id": "4",
            "vaga": "Vaga 4",
            "carro": "",
            "status": "0"
        },
        {
            "id": "5",
            "vaga": "Vaga_5",
            "carro": "",
            "status": "0"
        },
        {
            "id": "6",
            "vaga": "Vaga_6",
            "carro": "",
            "status": "0"
        },
        {
            "id": "7",
            "vaga": "Vaga_7",
            "carro": "",
            "status": "0"
        },
        {
            "id": "8",
            "vaga": "Vaga_8",
            "carro": "",
            "status": "0"
        }
    ]
}